README.md
cvcuda.cpython-310-x86_64-linux-gnu.so
libcvcuda.so
libcvcuda.so.0
libcvcuda.so.0.2.0
libgmock.a
libgtest.a
libnvcv_types.so
libnvcv_types.so.0
libnvcv_types.so.0.2.0
nvcv.cpython-310-x86_64-linux-gnu.so
cvcuda_test-0.0.21.dist-info/WHEEL
cvcuda_test-0.0.21.dist-info/METADATA
cvcuda_test-0.0.21.dist-info/licenses/LICENSE.md
cvcuda_test-0.0.21.dist-info/RECORD
